[
  {
    "link": "https://www.google.com/maps/place/Fire+bins/data=!4m7!3m6!1s0x88dd3f5f6727e28b:0xfdd2585f2e9fc327!8m2!3d28.0527413!4d-81.9458949!16s%2Fg%2F11vywq0xc4!19sChIJi-InZ18_3YgRJ8OfLl9Y0v0?authuser=0&hl=en&rclk=1",
    "lat": 28.0527413,
    "lon": -81.9458949
  },
  {
    "link": "https://www.google.com/maps/place/Santa+fe+store+bin+outlet/data=!4m7!3m6!1s0x80dd35a9d8cef163:0xdd0cec6928ea8513!8m2!3d33.7783773!4d-118.2626245!16s%2Fg%2F11vr_wr61z!19sChIJY_HO2Kk13YARE4XqKGnsDN0?authuser=0&hl=en&rclk=1",
    "lat": 33.7783773,
    "lon": -118.2626245
  },
  {
    "link": "https://www.google.com/maps/place/I+Heart+Bins/data=!4m7!3m6!1s0x87c0c07337300001:0x4a35b63b606aa215!8m2!3d46.423669!4d-129.9427086!16s%2Fg%2F11hd9kl1_v!19sChIJAQAwN3PAwIcRFaJqYDu2NUo?authuser=0&hl=en&rclk=1",
    "lat": 46.423669,
    "lon": -129.9427086
  },
  {
    "link": "https://www.google.com/maps/place/Bargain+Binzz/data=!4m7!3m6!1s0x89e6ddc6905cb07d:0x17737a6d571f9e7!8m2!3d46.423669!4d-129.9427086!16s%2Fg%2F11tybnjvyv!19sChIJfbBckMbd5okR5_lx1aY3dwE?authuser=0&hl=en&rclk=1",
    "lat": 46.423669,
    "lon": -129.9427086
  },
  {
    "link": "https://www.google.com/maps/place/Where+U+Bin/data=!4m7!3m6!1s0x8f146221a321c0c3:0x929e0278fcc81f7e!8m2!3d46.423669!4d-129.9427086!16s%2Fg%2F11pys74n6y!19sChIJw8AhoyFiFI8Rfh_I_HgCnpI?authuser=0&hl=en&rclk=1",
    "lat": 46.423669,
    "lon": -129.9427086
  },
  {
    "link": "https://www.google.com/maps/place/Uncle+Leo%27s+Bargain+Bin/data=!4m7!3m6!1s0x89b7fd5a73b45513:0xfa5ddc745b779509!8m2!3d46.423669!4d-129.9427086!16s%2Fg%2F11p64ycx9h!19sChIJE1W0c1r9t4kRCZV3W3TcXfo?authuser=0&hl=en&rclk=1",
    "lat": 46.423669,
    "lon": -129.9427086
  },
  {
    "link": "https://www.google.com/maps/place/Goodwill+Buy+the+Pound:+Williston/data=!4m7!3m6!1s0x4cca798aaef0e97b:0x9b6d95e0002fd1fa!8m2!3d44.4515587!4d-73.1188555!16s%2Fg%2F11fpr7_qmd!19sChIJe-nwrop5ykwR-tEvAOCVbZs?authuser=0&hl=en&rclk=1",
    "lat": 44.4515587,
    "lon": -73.1188555
  },
  {
    "link": "https://www.google.com/maps/place/Nana+Kim%27s+Bargin+Bin/data=!4m7!3m6!1s0x2c70402399cfa1c1:0x6eb2e5d4d0dbcb7f!8m2!3d46.423669!4d-129.9427086!16s%2Fg%2F11tx_vb7g_!19sChIJwaHPmSNAcCwRf8vb0NTlsm4?authuser=0&hl=en&rclk=1",
    "lat": 46.423669,
    "lon": -129.9427086
  },
  {
    "link": "https://www.google.com/maps/place/Closed/data=!4m7!3m6!1s0x8846f2ef9d393263:0x9bafdc2fa1b83f85!8m2!3d46.423669!4d-129.9427086!16s%2Fg%2F11rf7367ps!19sChIJYzI5ne_yRogRhT-4oS_cr5s?authuser=0&hl=en&rclk=1",
    "lat": 46.423669,
    "lon": -129.9427086
  },
  {
    "link": "https://www.google.com/maps/place/Bargain+Land/data=!4m7!3m6!1s0x864ea016753ab583:0xfe2a1aa26cc96c01!8m2!3d46.423669!4d-129.9427086!16s%2Fg%2F11rghpxkzk!19sChIJg7U6dRagToYRAWzJbKIaKv4?authuser=0&hl=en&rclk=1",
    "lat": 46.423669,
    "lon": -129.9427086
  },
  {
    "link": "https://www.google.com/maps/place/Carolina+bargain+bin/data=!4m7!3m6!1s0x67743cd1168f8f25:0x29db1585dd13e318!8m2!3d46.423669!4d-129.9427086!16s%2Fg%2F11wj9x14y0!19sChIJJY-PFtE8dGcRGOMT3YUV2yk?authuser=0&hl=en&rclk=1",
    "lat": 46.423669,
    "lon": -129.9427086
  },
  {
    "link": "https://www.google.com/maps/place/Bins4wins/data=!4m7!3m6!1s0x6a2f62ceeb4a911f:0x7172dac765e877f9!8m2!3d46.423669!4d-129.9427086!16s%2Fg%2F11t2lchjk6!19sChIJH5FK685iL2oR-XfoZcfacnE?authuser=0&hl=en&rclk=1",
    "lat": 46.423669,
    "lon": -129.9427086
  }
]